sun_mcp_calculator/__init__.py
sun_mcp_calculator/__main__.py
sun_mcp_calculator/caculator.py
sun_mcp_calculator-0.1.0.dist-info/METADATA
sun_mcp_calculator-0.1.0.dist-info/WHEEL
sun_mcp_calculator-0.1.0.dist-info/entry_points.txt
sun_mcp_calculator-0.1.0.dist-info/RECORD
