Metadata-Version: 2.4
Name: sun_mcp_calculator
Version: 0.1.0
Requires-Python: >=3.10
Requires-Dist: build>=1.2.2.post1
Requires-Dist: mcp
Requires-Dist: twine>=6.1.0
